setup.py
Restler.egg-info/PKG-INFO
Restler.egg-info/SOURCES.txt
Restler.egg-info/dependency_links.txt
Restler.egg-info/not-zip-safe
Restler.egg-info/requires.txt
Restler.egg-info/top_level.txt
restler/__init__.py
restler/controller.py
restler/entity.py
restler/tests/__init__.py