Metadata-Version: 1.0
Name: Restler
Version: 0.7.1
Summary: RESTful base controller for Pylons 1.0.
Home-page: https://bitbucket.org/wyatt/restler
Author: Wyatt L Baldwin
Author-email: self@wyattbaldwin.com
License: BSD/MIT
Keywords: web pylons controller REST WSGI
Platform: UNKNOWN
Classifier: Development Status :: 4 - Beta
Classifier: Environment :: Web Environment
Classifier: Framework :: Pylons
Classifier: Intended Audience :: Developers
Classifier: License :: OSI Approved :: MIT License
Classifier: Natural Language :: English
Classifier: Programming Language :: Python
